{
    "nodes":[
        {"id":"n00","name":"Ecosistema Alelo"},
        {"id":"n01","name":"Investimento Mídia"},
        {"id":"n02","name":"Investimento SEO"},
        {"id":"n03","name":"Outros Investimentos"},
        {"id":"n04","name":"Interações Fora do Site"},
        {"id":"n05","name":"Site - Mídia"},
        {"id":"n06","name":"Site - SEO"},
        {"id":"n07","name":"Site - Outros"},                
    ],
    "links":[
        {"id":"l01","source":0,"target":1,"value":90},
        {"id":"l02","source":0,"target":2,"value":10},
        {"id":"l03","source":0,"target":3,"value":0.01},
        {"id":"l04","source":1,"target":5,"value":35},
        {"id":"l05","source":2,"target":6,"value":25},
        {"id":"l06","source":3,"target":7,"value":40},
        {"id":"l07","source":1,"target":4,"value":15},
        {"id":"l08","source":5,"target":6,"value":15},
        {"id":"l09","source":6,"target":6,"value":35},
        {"id":"l10","source":7,"target":6,"value":35},
        {"id":"l11","source":4,"target":6,"value":20},
    ]
 }
